simple_logging_config-0.0.2.dist-info/METADATA
simple_logging_config-0.0.2.dist-info/WHEEL
simple_logging_config-0.0.2.dist-info/licenses/LICENSE.txt
simple_logging_config/__init__.py
simple_logging_config/_add_logging_arguments.py
simple_logging_config/_add_logging_level.py
simple_logging_config/_configure.py
simple_logging_config/_defaults.py
simple_logging_config/_exceptions.py
simple_logging_config/_file.py
simple_logging_config/_filters.py
simple_logging_config/_formatters.py
simple_logging_config/_level.py
simple_logging_config/_logging_config.py
simple_logging_config/_simple_logging_config.py
simple_logging_config/_singleton.py
simple_logging_config/_version.py
simple_logging_config/resources/configs.yaml
simple_logging_config/resources/default.yaml.jinja
simple_logging_config/resources/formatters.yaml
simple_logging_config/resources/handlers.yaml
simple_logging_config-0.0.2.dist-info/RECORD
