Metadata-Version: 2.1
Name: simple-logging-config
Version: 0.0.2
Summary: Simple Logging Config
Keywords: logging
Author-Email: srfoster65 <135555068+srfoster65@users.noreply.github.com>
License: MIT
Classifier: Programming Language :: Python :: 3
Project-URL: Documentation, https://srfoster65.github.io/simple_logging_config/
Project-URL: Source, https://github.com/srfoster65/simple_logging_config
Requires-Python: >=3.11
Requires-Dist: pyyaml>=6.0.1
Requires-Dist: jinja2>=3.1.2
Requires-Dist: arg-init>=0.0.4
